fglib2/__init__.py
fglib2/distributions.py
fglib2/graphs.py
fglib2/probabilistic_circuits.py
fglib2-1.1.5.dist-info/METADATA
fglib2-1.1.5.dist-info/WHEEL
fglib2-1.1.5.dist-info/top_level.txt
fglib2-1.1.5.dist-info/RECORD
