Metadata-Version: 2.1
Name: fglib2
Version: 1.1.5
Summary: Factor Graphs for probabilistic reasoning
Author-email: Tom Schierenbeck <tom_sch@uni-bremen.de>, Abdelrhman Bassiouny <abassiou@uni-bremen.de>, Alessandro Santonicola <ale_san@uni-bremen.de>
Project-URL: Source, https://github.com/tomsch420/fglib2
Project-URL: Bug Tracker, https://github.com/tomsch420/fglib2/issues
Keywords: probabilistic graphical models,factor graphs,belief propagation,sum product,probabilistic machine learning,probability theory,variables,reasoning under uncertainty
Classifier: Programming Language :: Python :: 3
Classifier: License :: OSI Approved :: MIT License
Classifier: Operating System :: OS Independent
Requires-Python: >=3.6
Requires-Dist: networkx >=3.0
Requires-Dist: numpy >=1.24.4
Requires-Dist: random-events >=1.2.5
Requires-Dist: tabulate >=0.9.0
Requires-Dist: probabilistic-model >=1.5.18
Requires-Dist: typing-extensions
